fhir_aggregator_client/__init__.py
fhir_aggregator_client/cli.py
fhir_aggregator_client/dataframer.py
fhir_aggregator_client/graph_definition.py
fhir_aggregator_client/visualizer.py
fhir_aggregator_client/vocabulary.py
fhir_aggregator_client/graph-definitions/CDACholangiocarcinomaGraph.yaml
fhir_aggregator_client/graph-definitions/ConditionGraph.yaml
fhir_aggregator_client/graph-definitions/DocumentReferenceGraph.yaml
fhir_aggregator_client/graph-definitions/PatientSurvivalGraph.yaml
fhir_aggregator_client/graph-definitions/ResearchStudyLinkIterate.yaml
fhir_aggregator_client/graph-definitions/ResearchStudyPartOf.yaml
fhir_aggregator_client-0.2.2.dist-info/LICENSE
fhir_aggregator_client-0.2.2.dist-info/METADATA
fhir_aggregator_client-0.2.2.dist-info/WHEEL
fhir_aggregator_client-0.2.2.dist-info/entry_points.txt
fhir_aggregator_client-0.2.2.dist-info/top_level.txt
fhir_aggregator_client-0.2.2.dist-info/RECORD
