Metadata-Version: 2.1
Name: fhir_aggregator_client
Version: 0.2.2
Home-page: https://github.com/FHIR-Aggregator/fhir-aggregator-client.git
Author: walsbr
Author-email: walsbr@ohsu.edu
License-File: LICENSE
Requires-Dist: click==8.1.7
Requires-Dist: requests==2.32.3
Requires-Dist: PyYAML==6.0.2
Requires-Dist: halo==0.0.31
Requires-Dist: httpx==0.28.1
Requires-Dist: fhir.resources==8.0.0b4
Requires-Dist: dotty-dict==1.3.1
Requires-Dist: pyvis==0.3.2
Requires-Dist: click-default-group==1.2.4
Requires-Dist: inflection==0.5.1
Requires-Dist: pandas
Requires-Dist: tabulate==0.9.0
Provides-Extra: dtale
Requires-Dist: dtale; extra == "dtale"
